<?xml version="1.0" encoding="UTF-8" standalone="no"?><studentRepository>
    <student id="1">
        <firstName>Razvanica</firstName>
        <lastName>Toma</lastName>
    </student>
    <student id="2">
        <firstName>Bianca</firstName>
        <lastName>Caluian</lastName>
    </student>
    <student id="3">
        <firstName>Cosmin</firstName>
        <lastName>Toma</lastName>
    </student>
    <student id="4">
        <firstName>Iulia</firstName>
        <lastName>Toma</lastName>
    </student>
</studentRepository>